main.py
set_up.py
mcp_server_moralis-0.1.2.dist-info/METADATA
mcp_server_moralis-0.1.2.dist-info/WHEEL
mcp_server_moralis-0.1.2.dist-info/entry_points.txt
mcp_server_moralis-0.1.2.dist-info/top_level.txt
mcp_server_moralis-0.1.2.dist-info/RECORD
