Metadata-Version: 2.4
Name: mcp-server-moralis
Version: 0.1.2
Summary: 基于Model Context Protocol (MCP)的Moralis区块链API服务器
Author: DAOCAT
License-Expression: MIT
Project-URL: Homepage, https://github.com/DAOCAT/mcp-server-moralis
Project-URL: Bug Tracker, https://github.com/DAOCAT/mcp-server-moralis/issues
Classifier: Programming Language :: Python :: 3
Classifier: Programming Language :: Python :: 3.12
Classifier: Operating System :: OS Independent
Requires-Python: >=3.12
Requires-Dist: httpx>=0.28.1
Requires-Dist: mcp>=1.6.0
Requires-Dist: python-dotenv>=1.0.0
Requires-Dist: moralis>=0.1.37
Requires-Dist: fastmcp>=1.0
Provides-Extra: dev
Requires-Dist: black>=24.1.0; extra == "dev"
Requires-Dist: isort>=5.12.0; extra == "dev"
Requires-Dist: pytest>=7.4.0; extra == "dev"
